parselglossy/__init__.py
parselglossy/api.py
parselglossy/check_template.py
parselglossy/cli.py
parselglossy/documentation.py
parselglossy/exceptions.py
parselglossy/generation.py
parselglossy/types.py
parselglossy/utils.py
parselglossy/validation.py
parselglossy/validation_plumbing.py
parselglossy/views.py
parselglossy/yaml_utils.py
parselglossy/grammars/__init__.py
parselglossy/grammars/atoms.py
parselglossy/grammars/getkw.py
parselglossy/grammars/lexer.py
parselglossy-0.8.1.dist-info/entry_points.txt
parselglossy-0.8.1.dist-info/LICENSE
parselglossy-0.8.1.dist-info/WHEEL
parselglossy-0.8.1.dist-info/METADATA
parselglossy-0.8.1.dist-info/RECORD
