Metadata-Version: 2.1
Name: parselglossy
Version: 0.8.1
Summary: Top-level package for parselglossy.
Home-page: https://parselglossy.readthedocs.io
License: MIT
Author: Roberto Di Remigio
Requires-Python: ~=3.7
Classifier: Intended Audience :: Developers
Classifier: License :: OSI Approved :: MIT License
Classifier: Natural Language :: English
Classifier: Programming Language :: Python :: 3
Classifier: Programming Language :: Python :: 3.7
Classifier: Programming Language :: Python :: 3.8
Classifier: Programming Language :: Python :: 3.9
Classifier: Programming Language :: Python :: 3.10
Classifier: Operating System :: OS Independent
Requires-Dist: click
Requires-Dist: pyparsing~=3.0
Requires-Dist: pyyaml
Requires-Dist: networkx
Requires-Dist: black==22.3.0 ; extra == "dev"
Requires-Dist: flake8 ; extra == "dev"
Requires-Dist: isort ; extra == "dev"
Requires-Dist: mypy ; extra == "dev"
Requires-Dist: types-PyYAML ; extra == "dev"
Requires-Dist: sphinx ; extra == "doc"
Requires-Dist: furo ; extra == "doc"
Requires-Dist: sphinx-copybutton ; extra == "doc"
Requires-Dist: sphinx-inline-tabs ; extra == "doc"
Requires-Dist: codecov ; extra == "test"
Requires-Dist: coverage ; extra == "test"
Requires-Dist: hypothesis ; extra == "test"
Requires-Dist: pytest ; extra == "test"
Requires-Dist: pytest-cov ; extra == "test"
Requires-Dist: pytest-sugar ; extra == "test"
Provides-Extra: dev
Provides-Extra: doc
Provides-Extra: test
